{"0": "Зато от лиса у меня есть хитрость",
 "1": "Неудачные отношения, это как один мусорный пакет усиливает запах другого мусорного пакета, но они оба винят друг друга, ища проблему в другом, а не в себе",
 "2": "Критикуешь - пошёл нахер",
 "3": "Извините, но ваше присутствие меня оскорбляет",
 "4": "Кажется, у нас новый официальный враг",
 "5": "Я не британец, чтобы бомбить от сообщений также, как они бомбили Дрезден",
 "6": "Я тя в друзья кину",
 "7": "Обьжаеши",
 "8": "Власть сносит крышу, но я снесу её первее",
 "9": "Отдай нуждающимся (мне)",
 "10": "Дерьмовистое говно обосралось недавно́",
 "11": "У тебя скорость",
 "12": "Спосибо на нит"
}